_selenium_webdriver_extender/__init__.py
_selenium_webdriver_extender/console.py
_selenium_webdriver_extender/driver.py
_selenium_webdriver_extender/file_handling.py
_selenium_webdriver_extender/form.py
_selenium_webdriver_extender/logger.py
_selenium_webdriver_extender/timer.py
selenium_webdriver_extender/__init__.py
selenium_webdriver_extender/__main__.py
selenium_webdriver_extender/cli.py
selenium_webdriver_extender-0.0.0.dist-info/AUTHORS.rst
selenium_webdriver_extender-0.0.0.dist-info/LICENSE
selenium_webdriver_extender-0.0.0.dist-info/METADATA
selenium_webdriver_extender-0.0.0.dist-info/WHEEL
selenium_webdriver_extender-0.0.0.dist-info/entry_points.txt
selenium_webdriver_extender-0.0.0.dist-info/top_level.txt
selenium_webdriver_extender-0.0.0.dist-info/RECORD
